core_evals/profbench/__init__.py
core_evals/profbench/framework.yml
core_evals/profbench/output.py
nvidia_profbench-25.11.dist-info/licenses/LICENSE
nvidia_profbench-25.11.dist-info/licenses/LICENSE-APACHE
profbench/__init__.py
profbench/run_best_llm_judge_on_generated_reports.py
profbench/run_llm_judge_on_provided_reports.py
profbench/run_report_generation.py
profbench/score_llm_judge.py
profbench/score_report_generation.py
profbench/utils.py
nvidia_profbench-25.11.dist-info/METADATA
nvidia_profbench-25.11.dist-info/WHEEL
nvidia_profbench-25.11.dist-info/entry_points.txt
nvidia_profbench-25.11.dist-info/top_level.txt
nvidia_profbench-25.11.dist-info/RECORD
