Metadata-Version: 2.4
Name: nvidia-profbench
Version: 25.11
Summary: Professional domain benchmark for evaluating LLMs on Physics PhD, Chemistry PhD, Finance MBA, and Consulting MBA tasks
Author: NVIDIA Corporation
License: Apache License 2.0
Project-URL: Homepage, https://github.com/nvidia/profbench
Project-URL: Repository, https://github.com/nvidia/profbench
Project-URL: Documentation, https://github.com/nvidia/profbench/blob/main/README.md
Keywords: llm,evaluation,benchmark,professional,phd,mba
Classifier: Development Status :: 5 - Production/Stable
Classifier: Programming Language :: Python :: 3
Classifier: License :: OSI Approved :: Apache Software License
Classifier: Operating System :: OS Independent
Requires-Python: >=3.8
License-File: LICENSE
License-File: LICENSE-APACHE
Requires-Dist: openai>=1.71.0
Requires-Dist: datasets>=2.14.7
Requires-Dist: huggingface-hub>=0.33.1
Requires-Dist: numpy
Requires-Dist: scikit-learn
Requires-Dist: tqdm
Requires-Dist: nemo-evaluator
Requires-Dist: google-genai
Provides-Extra: google
Requires-Dist: google-genai; extra == "google"
Provides-Extra: dev
Requires-Dist: pytest>=7.0; extra == "dev"
Requires-Dist: pytest-cov; extra == "dev"
Requires-Dist: black; extra == "dev"
Requires-Dist: flake8; extra == "dev"
Requires-Dist: mypy; extra == "dev"
Dynamic: license-file
